midi_player/__init__.py
midi_player/midi_player.py
midi_player/stylers.py
midi_player-0.5.1.dist-info/LICENSE
midi_player-0.5.1.dist-info/METADATA
midi_player-0.5.1.dist-info/WHEEL
midi_player-0.5.1.dist-info/top_level.txt
midi_player-0.5.1.dist-info/RECORD
