Metadata-Version: 2.1
Name: midi-player
Version: 0.5.1
Summary: Python launcher of animated MIDI player by @cifkao & @magenta
Home-page: https://github.com/drscotthawley/midi-player
Author: Scott H. Hawley
Author-email: scott.hawley@belmont.edu
License: MIT
Project-URL: Source, https://github.com/drscotthawley/midi-player
License-File: LICENSE
